shorthand_datetime/__init__.py
shorthand_datetime/shorthand.py
shorthand_datetime/version.py
shorthand_datetime-0.4.0.dist-info/LICENSE
shorthand_datetime-0.4.0.dist-info/WHEEL
shorthand_datetime-0.4.0.dist-info/METADATA
shorthand_datetime-0.4.0.dist-info/RECORD
