Metadata-Version: 2.3
Name: shorthand_datetime
Version: 0.4.0
Summary: Parse shorthand datetime strings in the Elasticsearch date math format. Inspired by Grafana.
Author-email: Wout Weijtjens <wout.weijtjens@gmail.com>, Pietro D'Antuono <pietro.dantuono@24sea.eu>
Classifier: Development Status :: 3 - Alpha
Classifier: Environment :: Console
Classifier: Intended Audience :: Science/Research
Classifier: Intended Audience :: Developers
Classifier: Intended Audience :: Information Technology
Classifier: License :: OSI Approved :: MIT License
Classifier: Natural Language :: English
Classifier: Operating System :: POSIX :: Linux
Classifier: Programming Language :: Python :: 3
Requires-Dist: pytz
Requires-Dist: twine ; extra == "build"
Requires-Dist: build ; extra == "build"
Requires-Dist: black==24.* ; extra == "dev"
Requires-Dist: mypy==1.* ; extra == "dev"
Requires-Dist: pycln==2.4.* ; extra == "dev"
Requires-Dist: isort==5.* ; extra == "dev"
Requires-Dist: ruff==0.* ; extra == "dev"
Requires-Dist: commitizen==3.* ; extra == "dev"
Requires-Dist: pre-commit==3.* ; extra == "dev"
Requires-Dist: types-PyYAML ; extra == "dev"
Requires-Dist: types-pytz ; extra == "dev"
Requires-Dist: types-requests ; extra == "dev"
Requires-Dist: sphinx ; extra == "docs"
Requires-Dist: sphinx-rtd-theme ; extra == "docs"
Requires-Dist: pytest ; extra == "test"
Requires-Dist: pytest-mock ; extra == "test"
Requires-Dist: hypothesis ; extra == "test"
Requires-Dist: pytest-cov ; extra == "test"
Project-URL: Bug-Tracker, https://github.com/wweijtje/shorthand-datetime/issues
Project-URL: Documentation, https://pypi.org/project/shorthand-datetime/
Project-URL: Homepage, https://pypi.org/project/shorthand-datetime/
Project-URL: Repository, https://github.com/wweijtje/shorthand-datetime/
Provides-Extra: build
Provides-Extra: dev
Provides-Extra: docs
Provides-Extra: test
